[
  {
    "Url": "assets/img/galleria/bread.jpg",
    "Title": "Placeholder Title Bread"
  },
  {
    "Url": "assets/img/galleria/assortedCupcakes.jpg",
    "Title": "Placeholder Title"
  },
  {
    "Url": "assets/img/galleria/cupcakeCookie.jpg",
    "Title": "Placeholder Title Cookie"
  },
  {
    "Url": "assets/img/galleria/flowerCookies.jpg",
    "Title": "Placeholder Title Cookies"
  },
  {
    "Url": "assets/img/galleria/Macaroons.jpg",
    "Title": "Placeholder Title"
  },
  {
    "Url": "assets/img/galleria/twoCupcakes.jpg",
    "Title": "Placeholder Title"
  }
]